pycounts_allabur/__init__.py
pycounts_allabur/plotting.py
pycounts_allabur/pycounts_allabur.py
pycounts_allabur-0.1.0.dist-info/LICENSE
pycounts_allabur-0.1.0.dist-info/METADATA
pycounts_allabur-0.1.0.dist-info/WHEEL
pycounts_allabur-0.1.0.dist-info/RECORD
